PyAxeTool/CMake.py
PyAxeTool/MD5.py
PyAxeTool/PyInstaller.py
PyAxeTool/__init__.py
oldbak/setup.py
pyaxetool-1.1.1.dist-info/METADATA
pyaxetool-1.1.1.dist-info/WHEEL
pyaxetool-1.1.1.dist-info/entry_points.txt
pyaxetool-1.1.1.dist-info/license_files/LICENSE
pyaxetool-1.1.1.dist-info/RECORD
